ShegongYanjiuzuWenzhangZhengli2017223/README.md
ShegongYanjiuzuWenzhangZhengli2017223/__init__.py
ShegongYanjiuzuWenzhangZhengli2017223/__main__.py
ShegongYanjiuzuWenzhangZhengli2017223/file.epub
ShegongYanjiuzuWenzhangZhengli2017223/index.html
ShegongYanjiuzuWenzhangZhengli2017223/css/__init__.py
ShegongYanjiuzuWenzhangZhengli2017223/css/annotations.css
ShegongYanjiuzuWenzhangZhengli2017223/css/main.css
ShegongYanjiuzuWenzhangZhengli2017223/css/normalize.css
ShegongYanjiuzuWenzhangZhengli2017223/css/popup.css
ShegongYanjiuzuWenzhangZhengli2017223/font/__init__.py
ShegongYanjiuzuWenzhangZhengli2017223/font/fontello.eot
ShegongYanjiuzuWenzhangZhengli2017223/font/fontello.svg
ShegongYanjiuzuWenzhangZhengli2017223/font/fontello.ttf
ShegongYanjiuzuWenzhangZhengli2017223/font/fontello.woff
ShegongYanjiuzuWenzhangZhengli2017223/img/__init__.py
ShegongYanjiuzuWenzhangZhengli2017223/img/annotator-glyph-sprite.png
ShegongYanjiuzuWenzhangZhengli2017223/img/annotator-icon-sprite.png
ShegongYanjiuzuWenzhangZhengli2017223/img/apple-touch-icon.png
ShegongYanjiuzuWenzhangZhengli2017223/img/cancelfullscreen.png
ShegongYanjiuzuWenzhangZhengli2017223/img/close.png
ShegongYanjiuzuWenzhangZhengli2017223/img/fullscreen.png
ShegongYanjiuzuWenzhangZhengli2017223/img/loader.gif
ShegongYanjiuzuWenzhangZhengli2017223/img/menu-icon.png
ShegongYanjiuzuWenzhangZhengli2017223/img/save.png
ShegongYanjiuzuWenzhangZhengli2017223/img/saved.png
ShegongYanjiuzuWenzhangZhengli2017223/img/settings-s.png
ShegongYanjiuzuWenzhangZhengli2017223/img/settings.png
ShegongYanjiuzuWenzhangZhengli2017223/img/star.png
ShegongYanjiuzuWenzhangZhengli2017223/js/__init__.py
ShegongYanjiuzuWenzhangZhengli2017223/js/epub.js
ShegongYanjiuzuWenzhangZhengli2017223/js/epub.min.js
ShegongYanjiuzuWenzhangZhengli2017223/js/epub.min.map
ShegongYanjiuzuWenzhangZhengli2017223/js/hooks.min.js
ShegongYanjiuzuWenzhangZhengli2017223/js/hooks.min.map
ShegongYanjiuzuWenzhangZhengli2017223/js/reader.js
shegong_yanjiuzu_wenzhang_zhengli_2017_2_23-2024.3.2.0.dist-info/METADATA
shegong_yanjiuzu_wenzhang_zhengli_2017_2_23-2024.3.2.0.dist-info/WHEEL
shegong_yanjiuzu_wenzhang_zhengli_2017_2_23-2024.3.2.0.dist-info/entry_points.txt
shegong_yanjiuzu_wenzhang_zhengli_2017_2_23-2024.3.2.0.dist-info/top_level.txt
shegong_yanjiuzu_wenzhang_zhengli_2017_2_23-2024.3.2.0.dist-info/RECORD
